fuzzy_reasoner/__init__.py
fuzzy_reasoner/prover/Goal.py
fuzzy_reasoner/prover/Proof.py
fuzzy_reasoner/prover/ProofState.py
fuzzy_reasoner/prover/SLDProver.py
fuzzy_reasoner/prover/__init__.py
fuzzy_reasoner/prover/operations/__init__.py
fuzzy_reasoner/prover/operations/recurse.py
fuzzy_reasoner/prover/operations/substitution.py
fuzzy_reasoner/prover/operations/unify.py
fuzzy_reasoner/similarity.py
fuzzy_reasoner/types/Atom.py
fuzzy_reasoner/types/Constant.py
fuzzy_reasoner/types/Knowledge.py
fuzzy_reasoner/types/Predicate.py
fuzzy_reasoner/types/Rule.py
fuzzy_reasoner/types/Variable.py
fuzzy_reasoner/types/__init__.py
fuzzy_reasoner-0.3.0.dist-info/LICENSE
fuzzy_reasoner-0.3.0.dist-info/WHEEL
fuzzy_reasoner-0.3.0.dist-info/METADATA
fuzzy_reasoner-0.3.0.dist-info/RECORD
