Metadata-Version: 2.1
Name: fuzzy-reasoner
Version: 0.3.0
Summary: Simple symbolic reasoner which supports fuzzy unification
Home-page: https://github.com/chanind/fuzzy-reasoner
License: MIT
Author: David Chanin
Author-email: chanindav@gmail.com
Requires-Python: >=3.7,<4.0
Classifier: License :: OSI Approved :: MIT License
Classifier: Programming Language :: Python :: 3
Classifier: Programming Language :: Python :: 3.10
Classifier: Programming Language :: Python :: 3.7
Classifier: Programming Language :: Python :: 3.8
Classifier: Programming Language :: Python :: 3.9
Requires-Dist: immutables (>=0.17,<0.18)
Requires-Dist: numpy (>=1.21.1,<2.0.0)
Project-URL: Repository, https://github.com/chanind/fuzzy-reasoner
